[
    {
        "sentenceNumber": 0,
        "sentenceText": "By ."
    },
    {
        "sentenceNumber": 1,
        "sentenceText": "Becky Barrow ."
    },
    {
        "sentenceNumber": 2,
        "sentenceText": "PUBLISHED: ."
    },
    {
        "sentenceNumber": 3,
        "sentenceText": "03:39 EST, 8 May 2012 ."
    },
    {
        "sentenceNumber": 4,
        "sentenceText": "| ."
    },
    {
        "sentenceNumber": 5,
        "sentenceText": "UPDATED: ."
    },
    {
        "sentenceNumber": 6,
        "sentenceText": "18:10 EST, 8 May 2012 ."
    },
    {
        "sentenceNumber": 7,
        "sentenceText": "Andrew Moss: He will be paid \u00a380,000 a month for the next year ."
    },
    {
        "sentenceNumber": 8,
        "sentenceText": "The boss of Britain\u2019s biggest insurance company will continue to receive his salary of \u00a380,000 a month for the next year despite his humiliating resignation yesterday."
    },
    {
        "sentenceNumber": 9,
        "sentenceText": "Andrew Moss, who has quit as chief executive of Aviva after a shareholder revolt, will receive a golden goodbye worth around \u00a31.75million in total."
    },
    {
        "sentenceNumber": 10,
        "sentenceText": "Last Thursday, 59 per cent of shareholder votes failed to back his gold-plated pay package worth up to \u00a35.2million last year."
    },
    {
        "sentenceNumber": 11,
        "sentenceText": "It was the latest chapter in the growing backlash against boardroom greed, nicknamed the Shareholder Spring."
    },
    {
        "sentenceNumber": 12,
        "sentenceText": "Yesterday the 54-year-old chief executive said he \u2018felt it was in the best interests of the company that he step aside to make way for new leadership\u2019."
    },
    {
        "sentenceNumber": 13,
        "sentenceText": "But Mr Moss, who has also sparked public criticism for leaving his wife of 25 years and their four children for a junior married colleague, Deidre Galvin, in 2009, will not be leaving empty-handed."
    },
    {
        "sentenceNumber": 14,
        "sentenceText": "Walked: Aviva Group chief executive Andrew Moss, who is to step down with immediate effect ."
    },
    {
        "sentenceNumber": 15,
        "sentenceText": "He will be paid his \u00a3960,000 \u2018basic\u2019 annual salary for the next year, equal to \u00a380,000 a month, unless he finds another job."
    },
    {
        "sentenceNumber": 16,
        "sentenceText": "Mr Moss will also get a \u00a3300,000 bonus payment, a cash injection of \u00a3209,000 into his pension pot in five years\u2019 time, deferred shares from a 2009 bonus, currently worth around \u00a3236,000, and a maximum of \u00a345,000 in legal and other expenses."
    },
    {
        "sentenceNumber": 17,
        "sentenceText": "He has two pensions from Aviva: one worth around \u00a3530,000 and one worth around \u00a32.75million, including the \u00a3209,000 payment."
    },
    {
        "sentenceNumber": 18,
        "sentenceText": "Mr Moss\u2019s departure was announced on the eve of today\u2019s Queen\u2019s Speech, which is expected to fire the starting gun on a crackdown on boardroom excess and empower shareholders to veto any examples of corporate excess."
    },
    {
        "sentenceNumber": 19,
        "sentenceText": "Bounce: Shares in the UK's largest insurer jumped five per cent following the announcement, suggesting investors approve of Mr Moss's departure ."
    },
    {
        "sentenceNumber": 20,
        "sentenceText": "Investor backing: The announcement was immediately followed by a spike in Aviva's shares ."
    },
    {
        "sentenceNumber": 21,
        "sentenceText": "At present, shareholders can vote ."
    },
    {
        "sentenceNumber": 22,
        "sentenceText": "against pay deals, but their votes are not binding on the company and ."
    },
    {
        "sentenceNumber": 23,
        "sentenceText": "directors can still receive the controversial pay and bonuses."
    },
    {
        "sentenceNumber": 24,
        "sentenceText": "The main ."
    },
    {
        "sentenceNumber": 25,
        "sentenceText": "role of such votes is to embarrass bosses and damage the firm\u2019s ."
    },
    {
        "sentenceNumber": 26,
        "sentenceText": "reputation."
    },
    {
        "sentenceNumber": 27,
        "sentenceText": "The mood of investors has turned ugly recently, triggering ."
    },
    {
        "sentenceNumber": 28,
        "sentenceText": "the departure of bosses at drugs company AstraZeneca and newspaper group ."
    },
    {
        "sentenceNumber": 29,
        "sentenceText": "Trinity Mirror."
    },
    {
        "sentenceNumber": 30,
        "sentenceText": "Turmoil: Aviva's St Helen's skyscraper looms in the City, where three CEOs have quit amid recent shareholder anger ."
    },
    {
        "sentenceNumber": 31,
        "sentenceText": "Yesterday, ."
    },
    {
        "sentenceNumber": 32,
        "sentenceText": "the chief executive of William Hill, Ralph Topping, was the latest ."
    },
    {
        "sentenceNumber": 33,
        "sentenceText": "victim, with nearly 50 per cent of the betting firm\u2019s shareholders ."
    },
    {
        "sentenceNumber": 34,
        "sentenceText": "voting against a \u00a31.2million bonus and a 8.3 per cent pay rise."
    },
    {
        "sentenceNumber": 35,
        "sentenceText": "At its ."
    },
    {
        "sentenceNumber": 36,
        "sentenceText": "annual meeting, one angry shareholder said: \u2018Chief executives are dining ."
    },
    {
        "sentenceNumber": 37,
        "sentenceText": "in the last chance saloon trying to take as much as they can as soon as ."
    },
    {
        "sentenceNumber": 38,
        "sentenceText": "possible.\u2019 Business ."
    },
    {
        "sentenceNumber": 39,
        "sentenceText": "Secretary Vince Cable, who has heavily criticised boardroom excess, said ."
    },
    {
        "sentenceNumber": 40,
        "sentenceText": "bosses are finally being \u2018brought back to reality\u2019."
    },
    {
        "sentenceNumber": 41,
        "sentenceText": "He welcomed the ."
    },
    {
        "sentenceNumber": 42,
        "sentenceText": "\u2018uprising\u2019 by shareholders as \u2018a healthy development\u2019, and said he is ."
    },
    {
        "sentenceNumber": 43,
        "sentenceText": "determined to stamp out \u2018rewards for failure\u2019."
    },
    {
        "sentenceNumber": 44,
        "sentenceText": "Since ."
    },
    {
        "sentenceNumber": 45,
        "sentenceText": "Mr Moss became chief executive in July 2007, Aviva\u2019s share price has ."
    },
    {
        "sentenceNumber": 46,
        "sentenceText": "more than halved, decimating the nest eggs of thousands of its smaller ."
    },
    {
        "sentenceNumber": 47,
        "sentenceText": "shareholders."
    },
    {
        "sentenceNumber": 48,
        "sentenceText": "Liberal Democrat ."
    },
    {
        "sentenceNumber": 49,
        "sentenceText": "Lord Oakeshott said: \u2018Shareholder votes must be binding, otherwise it ."
    },
    {
        "sentenceNumber": 50,
        "sentenceText": "just like a jury who acquit a man of a murder charge but the judge still ."
    },
    {
        "sentenceNumber": 51,
        "sentenceText": "gives him 20 years."
    },
    {
        "sentenceNumber": 52,
        "sentenceText": "What\u2019s the point?\u2019 Deborah ."
    },
    {
        "sentenceNumber": 53,
        "sentenceText": "Hargreaves, of the High Pay Centre campaign group, said: \u2018The irony is ."
    },
    {
        "sentenceNumber": 54,
        "sentenceText": "that Aviva was behind some of the recent pay revolts but, at the same ."
    },
    {
        "sentenceNumber": 55,
        "sentenceText": "time, they were not looking after their own backyard."
    },
    {
        "sentenceNumber": 56,
        "sentenceText": "\u2018This ."
    },
    {
        "sentenceNumber": 57,
        "sentenceText": "is what makes Mr Moss\u2019s payoff so intolerable."
    },
    {
        "sentenceNumber": 58,
        "sentenceText": "Aviva\u2019s corporate ."
    },
    {
        "sentenceNumber": 59,
        "sentenceText": "governance arm was lecturing others about pay and yet the company was ."
    },
    {
        "sentenceNumber": 60,
        "sentenceText": "ignoring its own advice.\u2019 Mr ."
    },
    {
        "sentenceNumber": 61,
        "sentenceText": "Moss ceased to be chief executive \u2018with immediate effect\u2019 yesterday, but ."
    },
    {
        "sentenceNumber": 62,
        "sentenceText": "he will not officially leave until the end of the month."
    },
    {
        "sentenceNumber": 63,
        "sentenceText": "Meanwhile, the average pay of bosses at Britain\u2019s biggest public companies rose by 11 per cent last year to \u00a33.65million, according to research published yesterday."
    },
    {
        "sentenceNumber": 64,
        "sentenceText": "The study, compiled for the BBC by Manifest, the adviser to shareholders, looked at the annual reports of 60 of the companies in the FTSE 100 index."
    },
    {
        "sentenceNumber": 65,
        "sentenceText": "On average, a chief executive gets a basic annual salary of \u00a3840,000, a long-term incentive plan of \u00a31.14million, a cash bonus of \u00a3689,000 plus several other lucrative perks, according to the research."
    },
    {
        "sentenceNumber": 66,
        "sentenceText": "But the average worker in the private sector is losing ground, according to a report from the pay experts Incomes Data Services."
    },
    {
        "sentenceNumber": 67,
        "sentenceText": "The average pay rise handed out by bosses to their cash-strapped workers between January and March was 3 per cent, it says."
    },
    {
        "sentenceNumber": 68,
        "sentenceText": "It comes at a time when inflation is 3.5 per cent."
    },
    {
        "sentenceNumber": 69,
        "sentenceText": "The report found that 8 per cent of workers, who typically are employed in manufacturing, construction or the not-for-profit sector, had their pay frozen."
    }
]